[
  {"id":"ro-ciorba-pui","nameEn":"Chicken vegetable soup (ciorbă de pui)","nameRo":"Ciorbă de pui","aliases":["ciorba de pui","supa de pui","supă pui","chicken soup"],"category":"Soups","kcal100":42,"p100":4.1,"c100":3.8,"f100":1.4,"fiber100":0.5,"servingG":350,"servingLabel":"Bowl ~350 ml","featured":true},
  {"id":"ro-ciorba-fasole","nameEn":"Bean soup (ciorbă de fasole)","nameRo":"Ciorbă de fasole","aliases":["ciorba de fasole","bean soup"],"category":"Soups","kcal100":55,"p100":3.2,"c100":8.5,"f100":1.2,"fiber100":2.8,"servingG":350,"servingLabel":"Bowl ~350 ml","featured":true},
  {"id":"ro-ciorba-burta","nameEn":"Tripe soup (ciorbă de burtă)","nameRo":"Ciorbă de burtă","aliases":["ciorba de burta","tripe soup"],"category":"Soups","kcal100":48,"p100":5.5,"c100":2.5,"f100":2.2,"fiber100":0.3,"servingG":350,"servingLabel":"Bowl ~350 ml","featured":true},
  {"id":"ro-ciorba-perisoare","nameEn":"Meatball soup (ciorbă de perişoare)","nameRo":"Ciorbă de perişoare","aliases":["ciorba de perisoare","perisoare","meatball soup"],"category":"Soups","kcal100":58,"p100":4.8,"c100":4.2,"f100":2.8,"fiber100":0.6,"servingG":350,"servingLabel":"Bowl ~350 ml","featured":false},
  {"id":"ro-ciorba-legume","nameEn":"Vegetable soup (ciorbă de legume)","nameRo":"Ciorbă de legume","aliases":["ciorba de legume","legume"],"category":"Soups","kcal100":28,"p100":1.2,"c100":4.5,"f100":0.8,"fiber100":1.4,"servingG":350,"servingLabel":"Bowl ~350 ml","featured":false},
  {"id":"ro-supa-galuste","nameEn":"Semolina dumpling soup (supă cu găluşte)","nameRo":"Supă cu găluşte","aliases":["supa cu galuste","galuste"],"category":"Soups","kcal100":52,"p100":3.5,"c100":6.2,"f100":1.8,"fiber100":0.4,"servingG":320,"servingLabel":"Bowl ~320 ml","featured":false},
  {"id":"ro-bors","nameEn":"Borsch base / sour soup (borş)","nameRo":"Borş","aliases":["bors","borș"],"category":"Soups","kcal100":12,"p100":0.5,"c100":2.8,"f100":0.1,"fiber100":0.2,"servingG":250,"servingLabel":"Cup diluted ~250 ml","featured":false},
  {"id":"ro-sarmale","nameEn":"Stuffed cabbage rolls (sarmale)","nameRo":"Sarmale","aliases":["sarmale cu mamaliga","varza umpluta","stuffed cabbage"],"category":"Traditional","kcal100":145,"p100":8.2,"c100":6.5,"f100":9.5,"fiber100":1.2,"servingG":220,"servingLabel":"3 rolls + sauce ~220 g","featured":true},
  {"id":"ro-mici","nameEn":"Grilled minced meat rolls (mici / mititei)","nameRo":"Mici (mititei)","aliases":["mititei","mici","grilled sausages"],"category":"Traditional","kcal100":280,"p100":14,"c100":2,"f100":23,"fiber100":0,"servingG":150,"servingLabel":"3 pieces ~150 g","featured":true},
  {"id":"ro-mamaliga","nameEn":"Polenta (mămăligă)","nameRo":"Mămăligă","aliases":["mamaliga","polenta"],"category":"Traditional","kcal100":85,"p100":2.4,"c100":18,"f100":0.6,"fiber100":1.5,"servingG":150,"servingLabel":"Portion ~150 g","featured":true},
  {"id":"ro-mamaliga-branza","nameEn":"Polenta with cheese & cream","nameRo":"Mămăligă cu brânză şi smântână","aliases":["mamaliga cu branza","balmos"],"category":"Traditional","kcal100":165,"p100":7.5,"c100":16,"f100":8.5,"fiber100":1.2,"servingG":200,"servingLabel":"Portion ~200 g","featured":true},
  {"id":"ro-tochitura","nameEn":"Pork stew Moldovan style (tochitură)","nameRo":"Tochitură","aliases":["tochitura","moldovenesc"],"category":"Traditional","kcal100":210,"p100":12,"c100":3.5,"f100":16,"fiber100":0.3,"servingG":180,"servingLabel":"Plate ~180 g","featured":false},
  {"id":"ro-fasole-batuta","nameEn":"Mashed beans with onion (fasole bătută)","nameRo":"Fasole bătută","aliases":["fasole batuta"],"category":"Traditional","kcal100":115,"p100":6.8,"c100":14,"f100":3.5,"fiber100":4.2,"servingG":150,"servingLabel":"~150 g","featured":false},
  {"id":"ro-fasole-carnati","nameEn":"Beans with smoked sausage","nameRo":"Fasole cu cârnaţi","aliases":["fasole cu carnati"],"category":"Traditional","kcal100":135,"p100":8.5,"c100":12,"f100":5.5,"fiber100":3.5,"servingG":220,"servingLabel":"Plate ~220 g","featured":false},
  {"id":"ro-iahnie","nameEn":"Seasoned beans (iahnie)","nameRo":"Iahnie de fasole","aliases":["iahnie","fasole fiarta"],"category":"Traditional","kcal100":102,"p100":6.2,"c100":15,"f100":2.2,"fiber100":4.5,"servingG":180,"servingLabel":"~180 g","featured":false},
  {"id":"ro-ghiveci","nameEn":"Vegetable stew (ghiveci)","nameRo":"Ghiveci de legume","aliases":["ghiveci"],"category":"Vegetarian","kcal100":48,"p100":1.8,"c100":6.5,"f100":1.9,"fiber100":2.2,"servingG":200,"servingLabel":"~200 g","featured":false},
  {"id":"ro-ardei-umpluti","nameEn":"Stuffed peppers","nameRo":"Ardei umpluţi","aliases":["ardei umpluti"],"category":"Traditional","kcal100":95,"p100":6.5,"c100":8.5,"f100":4.2,"fiber100":1.8,"servingG":220,"servingLabel":"2 peppers ~220 g","featured":false},
  {"id":"ro-dovlecei-pane","nameEn":"Fried courgette (dovlecei pane)","nameRo":"Dovlecei pane","aliases":["dovlecei pane","zucchini fried"],"category":"Traditional","kcal100":165,"p100":4.2,"c100":12,"f100":11,"fiber100":1.2,"servingG":150,"servingLabel":"~150 g fried","featured":false},
  {"id":"ro-varza-calita","nameEn":"Braised cabbage","nameRo":"Varză călită","aliases":["varza calita"],"category":"Sides","kcal100":72,"p100":1.8,"c100":8.5,"f100":3.8,"fiber100":2.5,"servingG":160,"servingLabel":"~160 g","featured":false},
  {"id":"ro-tocana-pui","nameEn":"Chicken stew (tocăniţă)","nameRo":"Tocăniţă de pui","aliases":["tocana pui","tocanita"],"category":"Traditional","kcal100":105,"p100":11,"c100":4.5,"f100":4.8,"fiber100":1.0,"servingG":200,"servingLabel":"~200 g","featured":false},
  {"id":"ro-drob","nameEn":"Lamb haggis-style (drob)","nameRo":"Drob de miel","aliases":["drob"],"category":"Traditional","kcal100":195,"p100":14,"c100":4.5,"f100":13,"fiber100":0.4,"servingG":120,"servingLabel":"Slice ~120 g","featured":false},
  {"id":"ro-snitel-pui","nameEn":"Breaded chicken schnitzel","nameRo":"Şniţel de pui","aliases":["snitel pui","snitzel pui"],"category":"Meat","kcal100":220,"p100":16,"c100":12,"f100":12,"fiber100":0.6,"servingG":150,"servingLabel":"1 piece ~150 g","featured":true},
  {"id":"ro-snitel-porc","nameEn":"Breaded pork schnitzel","nameRo":"Şniţel de porc","aliases":["snitel porc"],"category":"Meat","kcal100":265,"p100":14,"c100":11,"f100":17,"fiber100":0.5,"servingG":160,"servingLabel":"1 piece ~160 g","featured":false},
  {"id":"ro-piept-pui-gratar","nameEn":"Grilled chicken breast","nameRo":"Piept de pui la grătar","aliases":["piept pui","grilled chicken"],"category":"Meat","kcal100":165,"p100":31,"c100":0,"f100":3.6,"fiber100":0,"servingG":150,"servingLabel":"~150 g","featured":true},
  {"id":"ro-pulpa-pui-cuptor","nameEn":"Roasted chicken thigh","nameRo":"Pulpă de pui la cuptor","aliases":["pulpa pui","chicken thigh"],"category":"Meat","kcal100":195,"p100":18,"c100":0.2,"f100":13,"fiber100":0,"servingG":140,"servingLabel":"1 thigh ~140 g","featured":false},
  {"id":"ro-friptura-porc","nameEn":"Roast pork","nameRo":"Friptură de porc","aliases":["porc la cuptor","friptura"],"category":"Meat","kcal100":260,"p100":16,"c100":0,"f100":21,"fiber100":0,"servingG":120,"servingLabel":"~120 g lean","featured":false},
  {"id":"ro-paste-simple","nameEn":"Boiled pasta (plain)","nameRo":"Paste fierte simple","aliases":["paste","spaghetti","macaroane"],"category":"Staples","kcal100":158,"p100":5.5,"c100":31,"f100":0.9,"fiber100":1.8,"servingG":180,"servingLabel":"Cooked ~180 g","featured":true},
  {"id":"ro-orez-fiert","nameEn":"Boiled white rice","nameRo":"Orez fiert","aliases":["orez","rice boiled"],"category":"Staples","kcal100":130,"p100":2.7,"c100":28,"f100":0.3,"fiber100":0.4,"servingG":150,"servingLabel":"~150 g cooked","featured":true},
  {"id":"ro-pilaf","nameEn":"Rice pilaf with vegetables","nameRo":"Pilaf cu legume","aliases":["pilaf"],"category":"Staples","kcal100":125,"p100":2.8,"c100":22,"f100":2.8,"fiber100":1.2,"servingG":180,"servingLabel":"~180 g","featured":false},
  {"id":"ro-cartofi-copti","nameEn":"Baked potato","nameRo":"Cartofi copţi","aliases":["cartofi copti","baked potato"],"category":"Staples","kcal100":93,"p100":2.5,"c100":21,"f100":0.1,"fiber100":2.2,"servingG":200,"servingLabel":"1 medium ~200 g","featured":true},
  {"id":"ro-cartofi-piure","nameEn":"Mashed potato with milk/butter","nameRo":"Cartofi piure","aliases":["piure","mashed potato"],"category":"Staples","kcal100":105,"p100":2,"c100":15,"f100":4.2,"fiber100":1.5,"servingG":180,"servingLabel":"~180 g","featured":false},
  {"id":"ro-cartofi-prajiti","nameEn":"French fries","nameRo":"Cartofi prăjiţi","aliases":["cartofi prajiti","fries"],"category":"Staples","kcal100":312,"p100":3.4,"c100":41,"f100":15,"fiber100":3.8,"servingG":120,"servingLabel":"Small portion ~120 g","featured":false},
  {"id":"ro-salata-boeuf","nameEn":"Beef salad (salată de boeuf)","nameRo":"Salată de boeuf","aliases":["salata boeuf","olivier style"],"category":"Salads","kcal100":185,"p100":6.5,"c100":9.5,"f100":13.5,"fiber100":1.2,"servingG":150,"servingLabel":"~150 g","featured":false},
  {"id":"ro-salata-orientala","nameEn":"Oriental bean salad","nameRo":"Salată orientală","aliases":["salata orientala","bean salad"],"category":"Salads","kcal100":115,"p100":5.5,"c100":12,"f100":5.2,"fiber100":3.5,"servingG":160,"servingLabel":"~160 g","featured":false},
  {"id":"ro-salata-verde","nameEn":"Green salad with oil","nameRo":"Salată verde cu ulei","aliases":["salata verde","lettuce"],"category":"Salads","kcal100":45,"p100":1.2,"c100":2.5,"f100":3.8,"fiber100":1.2,"servingG":120,"servingLabel":"Bowl ~120 g","featured":false},
  {"id":"ro-muraturi","nameEn":"Pickled vegetables","nameRo":"Murături","aliases":["castraveti murati","muraturi"],"category":"Sides","kcal100":14,"p100":0.8,"c100":2.5,"f100":0.2,"fiber100":1.2,"servingG":80,"servingLabel":"Side ~80 g","featured":false},
  {"id":"ro-ou-fiert","nameEn":"Boiled egg","nameRo":"Ou fiert","aliases":["ou","egg boiled"],"category":"Breakfast","kcal100":155,"p100":13,"c100":1.1,"f100":11,"fiber100":0,"servingG":50,"servingLabel":"1 large egg ~50 g","featured":true},
  {"id":"ro-ou-ochiuri","nameEn":"Fried eggs","nameRo":"Ochiuri","aliases":["ou prajit","fried egg"],"category":"Breakfast","kcal100":185,"p100":12.5,"c100":1.2,"f100":14.5,"fiber100":0,"servingG":110,"servingLabel":"2 eggs + oil ~110 g","featured":false},
  {"id":"ro-omleta","nameEn":"Omelette","nameRo":"Omletă","aliases":["omleta"],"category":"Breakfast","kcal100":145,"p100":10.5,"c100":1.5,"f100":11,"fiber100":0,"servingG":120,"servingLabel":"~120 g","featured":false},
  {"id":"ro-parizer","nameEn":"Cold cuts / parizer slice","nameRo":"Parizer","aliases":["parizer","parizer felie"],"category":"Meat","kcal100":260,"p100":11,"c100":2,"f100":23,"fiber100":0,"servingG":40,"servingLabel":"2 slices ~40 g","featured":false},
  {"id":"ro-salam-vara","nameEn":"Summer sausage slice","nameRo":"Salam de vară","aliases":["salam de vara"],"category":"Meat","kcal100":305,"p100":13,"c100":1.5,"f100":27,"fiber100":0,"servingG":30,"servingLabel":"~30 g","featured":false},
  {"id":"ro-pastrama","nameEn":"Pastrami slices","nameRo":"Pastramă","aliases":["pastrama"],"category":"Meat","kcal100":210,"p100":22,"c100":1.2,"f100":13,"fiber100":0,"servingG":40,"servingLabel":"~40 g","featured":false},
  {"id":"ro-ton-conserva","nameEn":"Canned tuna in water","nameRo":"Ton în conservă (apă)","aliases":["ton","tuna can"],"category":"Fish","kcal100":116,"p100":26,"c100":0,"f100":0.8,"fiber100":0,"servingG":100,"servingLabel":"Drained ~100 g","featured":false},
  {"id":"ro-scumbie","nameEn":"Grilled herring / mackerel","nameRo":"Scrumbie la grătar","aliases":["scrumbie","hering"],"category":"Fish","kcal100":195,"p100":18,"c100":0,"f100":13,"fiber100":0,"servingG":120,"servingLabel":"~120 g","featured":false},
  {"id":"ro-telemea","nameEn":"Telemea brined cheese","nameRo":"Telemea","aliases":["telemea de vaca","branza telemea"],"category":"Dairy","kcal100":260,"p100":17,"c100":2.5,"f100":20,"fiber100":0,"servingG":40,"servingLabel":"Slice ~40 g","featured":true},
  {"id":"ro-branza-burduf","nameEn":"Burduf cheese (sheep)","nameRo":"Brânză de burduf","aliases":["branza burduf"],"category":"Dairy","kcal100":310,"p100":18,"c100":2,"f100":25,"fiber100":0,"servingG":35,"servingLabel":"~35 g","featured":false},
  {"id":"ro-urda","nameEn":"Urdă fresh cheese","nameRo":"Urdă","aliases":["urda"],"category":"Dairy","kcal100":115,"p100":12,"c100":3.5,"f100":5.5,"fiber100":0,"servingG":50,"servingLabel":"~50 g","featured":false},
  {"id":"ro-cascaval","nameEn":"Cașcaval / yellow cheese","nameRo":"Caşcaval","aliases":["cascaval","kashkaval"],"category":"Dairy","kcal100":325,"p100":24,"c100":2.5,"f100":24,"fiber100":0,"servingG":40,"servingLabel":"Slice ~40 g","featured":true},
  {"id":"ro-cas-proaspat","nameEn":"Fresh caș cheese","nameRo":"Caş proaspăt","aliases":["cas proaspat"],"category":"Dairy","kcal100":135,"p100":12,"c100":3.2,"f100":8.5,"fiber100":0,"servingG":50,"servingLabel":"~50 g","featured":false},
  {"id":"ro-smantana-20","nameEn":"Sour cream 20%","nameRo":"Smântână 20%","aliases":["smantana","cream sour"],"category":"Dairy","kcal100":205,"p100":2.8,"c100":3.5,"f100":20,"fiber100":0,"servingG":30,"servingLabel":"2 tbsp ~30 g","featured":false},
  {"id":"ro-smantana-30","nameEn":"Sour cream 30%","nameRo":"Smântână 30%","aliases":["smantana grasa"],"category":"Dairy","kcal100":290,"p100":2.2,"c100":3,"f100":30,"fiber100":0,"servingG":25,"servingLabel":"~25 g","featured":false},
  {"id":"ro-iaurt-natur","nameEn":"Plain yogurt 3.5%","nameRo":"Iaurt natur","aliases":["iaurt","yogurt plain"],"category":"Dairy","kcal100":78,"p100":4.2,"c100":5.5,"f100":3.5,"fiber100":0,"sugar100":5.5,"servingG":150,"servingLabel":"Cup ~150 g","featured":true},
  {"id":"ro-iaurt-0","nameEn":"Fat-free yogurt","nameRo":"Iaurt 0% grăsimi","aliases":["iaurt 0"],"category":"Dairy","kcal100":48,"p100":4.8,"c100":7.5,"f100":0.2,"fiber100":0,"sugar100":7,"servingG":150,"servingLabel":"~150 g","featured":false},
  {"id":"ro-lapte-35","nameEn":"Whole milk 3.5%","nameRo":"Lapte 3.5%","aliases":["lapte","milk whole"],"category":"Dairy","kcal100":64,"p100":3.3,"c100":4.8,"f100":3.5,"fiber100":0,"sugar100":4.8,"servingG":250,"servingLabel":"Glass ~250 ml","featured":true},
  {"id":"ro-lapte-batut","nameEn":"Buttermilk / lapte bătut","nameRo":"Lapte bătut","aliases":["lapte batut","kefir plain"],"category":"Dairy","kcal100":42,"p100":3.2,"c100":4.5,"f100":1.2,"fiber100":0,"servingG":250,"servingLabel":"~250 ml","featured":false},
  {"id":"ro-kefir","nameEn":"Kefir","nameRo":"Kefir","aliases":["kefir"],"category":"Dairy","kcal100":55,"p100":3.5,"c100":4.2,"f100":3,"fiber100":0,"servingG":250,"servingLabel":"~250 ml","featured":false},
  {"id":"ro-franzela","nameEn":"White bread (franzelă)","nameRo":"Franzelă","aliases":["paine alba","bread white"],"category":"Bakery","kcal100":265,"p100":8.5,"c100":50,"f100":3.2,"fiber100":2.5,"servingG":50,"servingLabel":"1 slice ~50 g","featured":true},
  {"id":"ro-paine-integrala","nameEn":"Wholemeal bread","nameRo":"Pâine integrală","aliases":["paine integrala","whole grain bread"],"category":"Bakery","kcal100":240,"p100":9.5,"c100":42,"f100":4.2,"fiber100":6.5,"servingG":45,"servingLabel":"1 slice ~45 g","featured":true},
  {"id":"ro-covrig-sarat","nameEn":"Salted pretzel (covrig)","nameRo":"Covrig sărat","aliases":["covrig","pretzel"],"category":"Bakery","kcal100":290,"p100":9,"c100":52,"f100":5.5,"fiber100":2.2,"servingG":55,"servingLabel":"1 piece ~55 g","featured":true},
  {"id":"ro-covrig-dulce","nameEn":"Sweet pretzel / pastry","nameRo":"Covrig dulce","aliases":["covrig dulce"],"category":"Bakery","kcal100":355,"p100":7.5,"c100":58,"f100":10,"fiber100":2,"servingG":60,"servingLabel":"~60 g","featured":false},
  {"id":"ro-cozonac","nameEn":"Cozonac (sweet bread)","nameRo":"Cozonac","aliases":["cozonac nuca"],"category":"Sweets","kcal100":365,"p100":8.5,"c100":48,"f100":16,"fiber100":2.5,"servingG":80,"servingLabel":"Slice ~80 g","featured":true},
  {"id":"ro-papanasi","nameEn":"Papanași (cheese doughnuts)","nameRo":"Papanași","aliases":["papanasi"],"category":"Sweets","kcal100":285,"p100":8.5,"c100":32,"f100":14,"fiber100":0.8,"servingG":150,"servingLabel":"Portion ~150 g","featured":true},
  {"id":"ro-placinta-branza","nameEn":"Cheese pie (plăcintă)","nameRo":"Plăcintă cu brânză","aliases":["placinta cu branza"],"category":"Sweets","kcal100":298,"p100":9.5,"c100":32,"f100":14.5,"fiber100":1.2,"servingG":120,"servingLabel":"Piece ~120 g","featured":false},
  {"id":"ro-placinta-mere","nameEn":"Apple pie slice","nameRo":"Plăcintă cu mere","aliases":["placinta cu mere"],"category":"Sweets","kcal100":265,"p100":3.5,"c100":38,"f100":11,"fiber100":2,"servingG":110,"servingLabel":"~110 g","featured":false},
  {"id":"ro-gogosi","nameEn":"Doughnuts","nameRo":"Gogoşi","aliases":["gogosi","donuts"],"category":"Sweets","kcal100":385,"p100":5.5,"c100":44,"f100":21,"fiber100":1.5,"servingG":65,"servingLabel":"1 piece ~65 g","featured":false},
  {"id":"ro-halva","nameEn":"Halva","nameRo":"Halva","aliases":["halva"],"category":"Sweets","kcal100":520,"p100":11,"c100":48,"f100":32,"fiber100":3.5,"servingG":35,"servingLabel":"~35 g","featured":false},
  {"id":"ro-zacusca","nameEn":"Zacuscă (vegetable spread)","nameRo":"Zacuscă","aliases":["zacusca"],"category":"Preserves","kcal100":95,"p100":1.8,"c100":8.5,"f100":5.8,"fiber100":2.8,"servingG":30,"servingLabel":"1 tbsp ~30 g","featured":true},
  {"id":"ro-gem","nameEn":"Jam / gem","nameRo":"Gem","aliases":["dulceata","jam"],"category":"Preserves","kcal100":265,"p100":0.5,"c100":65,"f100":0.2,"fiber100":1,"sugar100":58,"servingG":20,"servingLabel":"1 tbsp ~20 g","featured":false},
  {"id":"ro-miere","nameEn":"Honey","nameRo":"Miere","aliases":["honey"],"category":"Preserves","kcal100":304,"p100":0.3,"c100":82,"f100":0,"fiber100":0,"sugar100":82,"servingG":15,"servingLabel":"1 tbsp ~15 g","featured":false},
  {"id":"ro-mere","nameEn":"Apple","nameRo":"Mere","aliases":["mar","apple"],"category":"Fruit","kcal100":52,"p100":0.3,"c100":14,"f100":0.2,"fiber100":2.4,"sugar100":10,"servingG":150,"servingLabel":"1 medium ~150 g","featured":false},
  {"id":"ro-banane","nameEn":"Banana","nameRo":"Banane","aliases":["banana"],"category":"Fruit","kcal100":89,"p100":1.1,"c100":23,"f100":0.3,"fiber100":2.6,"sugar100":12,"servingG":120,"servingLabel":"1 medium ~120 g","featured":false},
  {"id":"ro-rosii","nameEn":"Tomato","nameRo":"Roşii","aliases":["rosii","tomato"],"category":"Vegetables","kcal100":18,"p100":0.9,"c100":3.9,"f100":0.2,"fiber100":1.2,"servingG":120,"servingLabel":"~120 g","featured":false},
  {"id":"ro-castraveti","nameEn":"Cucumber","nameRo":"Castraveţi","aliases":["castraveti"],"category":"Vegetables","kcal100":15,"p100":0.7,"c100":3.6,"f100":0.1,"fiber100":0.5,"servingG":100,"servingLabel":"~100 g","featured":false},
  {"id":"ro-naut-fiert","nameEn":"Boiled chickpeas","nameRo":"Năut fiert","aliases":["naut","chickpeas"],"category":"Legumes","kcal100":164,"p100":8.9,"c100":27,"f100":2.6,"fiber100":7.6,"servingG":150,"servingLabel":"~150 g","featured":false},
  {"id":"ro-linte-fiarta","nameEn":"Boiled lentils","nameRo":"Linte fiartă","aliases":["linte"],"category":"Legumes","kcal100":116,"p100":9,"c100":20,"f100":0.4,"fiber100":7.9,"servingG":150,"servingLabel":"~150 g","featured":false},
  {"id":"ro-shaorma-mica","nameEn":"Small shawarma (estimate)","nameRo":"Şaorma mică (estimare)","aliases":["shaorma","shawarma"],"category":"Street food","kcal100":195,"p100":11,"c100":18,"f100":9.5,"fiber100":1.5,"servingG":280,"servingLabel":"Small wrap ~280 g","featured":false},
  {"id":"ro-pizza-felie","nameEn":"Pizza slice (estimate)","nameRo":"Pizza (felie)","aliases":["pizza"],"category":"Street food","kcal100":260,"p100":11,"c100":30,"f100":10.5,"fiber100":1.8,"servingG":120,"servingLabel":"1 slice ~120 g","featured":false},
  {"id":"ro-merdenea","nameEn":"Cheese pastry (merdenea)","nameRo":"Merdenea","aliases":["merdenea"],"category":"Bakery","kcal100":385,"p100":8.5,"c100":38,"f100":22,"fiber100":1.5,"servingG":85,"servingLabel":"~85 g","featured":false},
  {"id":"ro-gris-cu-lapte","nameEn":"Semolina with milk (griş cu lapte)","nameRo":"Griş cu lapte","aliases":["gris cu lapte"],"category":"Desserts","kcal100":95,"p100":3.2,"c100":15,"f100":2.8,"fiber100":0.3,"servingG":200,"servingLabel":"Bowl ~200 g","featured":false},
  {"id":"ro-carnati-proaspeti","nameEn":"Fresh pork sausages (grilled)","nameRo":"Cârnaţi proaspeţi la grătar","aliases":["carnati proaspeti"],"category":"Meat","kcal100":305,"p100":13,"c100":1.5,"f100":27,"fiber100":0,"servingG":100,"servingLabel":"2 links ~100 g","featured":false},
  {"id":"ro-slana","nameEn":"Slănină / salt pork","nameRo":"Slănină","aliases":["slana","bacon slab"],"category":"Meat","kcal100":520,"p100":9,"c100":0,"f100":53,"fiber100":0,"servingG":30,"servingLabel":"Thin slice ~30 g","featured":false},
  {"id":"ro-cascaval-pane","nameEn":"Fried breaded cheese","nameRo":"Caşcaval pane","aliases":["cascaval pane"],"category":"Street food","kcal100":315,"p100":14,"c100":18,"f100":21,"fiber100":0.8,"servingG":90,"servingLabel":"2 pieces ~90 g","featured":false},
  {"id":"ro-branza-topita","nameEn":"Processed cheese triangle","nameRo":"Brânză topită","aliases":["branza topita","triunghi"],"category":"Dairy","kcal100":285,"p100":16,"c100":4.5,"f100":22,"fiber100":0,"servingG":25,"servingLabel":"2 triangles ~25 g","featured":false},
  {"id":"ro-cereale-copii","nameEn":"Breakfast cereal with milk (estimate)","nameRo":"Cereale cu lapte","aliases":["cereale","corn flakes"],"category":"Breakfast","kcal100":360,"p100":8.5,"c100":72,"f100":5.5,"fiber100":3,"servingG":55,"servingLabel":"Bowl dry+calc ~55 g eq","featured":false},
  {"id":"ro-ciocolata","nameEn":"Milk chocolate","nameRo":"Ciocolată cu lapte","aliases":["ciocolata","chocolate"],"category":"Sweets","kcal100":535,"p100":7.5,"c100":58,"f100":30,"fiber100":3.5,"sugar100":52,"servingG":25,"servingLabel":"~25 g","featured":false},
  {"id":"ro-nuci","nameEn":"Walnuts","nameRo":"Nuci","aliases":["walnuts","nuci"],"category":"Snacks","kcal100":654,"p100":15,"c100":14,"f100":65,"fiber100":6.7,"servingG":28,"servingLabel":"Small handful ~28 g","featured":false},
  {"id":"ro-alune","nameEn":"Peanuts roasted","nameRo":"Alune prăjite","aliases":["alune","peanuts"],"category":"Snacks","kcal100":585,"p100":24,"c100":18,"f100":49,"fiber100":8.5,"servingG":30,"servingLabel":"~30 g","featured":false},
  {"id":"ro-apa-minerala","nameEn":"Mineral water","nameRo":"Apă minerală","aliases":["apa minerala","sparkling water"],"category":"Drinks","kcal100":0,"p100":0,"c100":0,"f100":0,"fiber100":0,"servingG":330,"servingLabel":"Bottle ~330 ml","featured":false},
  {"id":"ro-suc-mere","nameEn":"Apple juice","nameRo":"Suc de mere","aliases":["suc mere","apple juice"],"category":"Drinks","kcal100":46,"p100":0.1,"c100":11,"f100":0.1,"fiber100":0.2,"sugar100":10,"servingG":250,"servingLabel":"Glass ~250 ml","featured":false},
  {"id":"ro-cafea-cu-lapte","nameEn":"Coffee with milk","nameRo":"Cafea cu lapte","aliases":["cafea latte","coffee milk"],"category":"Drinks","kcal100":35,"p100":1.8,"c100":3.5,"f100":1.2,"fiber100":0,"servingG":200,"servingLabel":"Cup ~200 ml","featured":false},
  {"id":"ro-ciorba-de-burta-small","nameEn":"Tripe soup (lighter estimate)","nameRo":"Ciorbă de burtă (variantă uşoară)","aliases":[],"category":"Soups","kcal100":38,"p100":4.8,"c100":2.2,"f100":1.5,"fiber100":0.2,"servingG":350,"servingLabel":"Bowl ~350 ml","featured":false},
  {"id":"ro-mic-dejun-taraneasca","nameEn":"Farmer breakfast (eggs+susage+bread est.)","nameRo":"Mic dejun ţărănesc (estimare)","aliases":["mic dejun"],"category":"Breakfast","kcal100":195,"p100":12,"c100":14,"f100":10.5,"fiber100":1.2,"servingG":280,"servingLabel":"Plate ~280 g","featured":false},
  {"id":"ro-ciorba-de-pui-legume","nameEn":"Chicken soup with noodles","nameRo":"Ciorbă de pui cu tăiţei","aliases":["ciorba cu taitei","taitei"],"category":"Soups","kcal100":48,"p100":3.8,"c100":5.5,"f100":1.2,"fiber100":0.4,"servingG":350,"servingLabel":"Bowl ~350 ml","featured":false},
  {"id":"ro-ciorba-de-peste","nameEn":"Fish soup","nameRo":"Ciorbă de peşte","aliases":["ciorba de peste"],"category":"Soups","kcal100":52,"p100":6.2,"c100":2.8,"f100":2.0,"fiber100":0.3,"servingG":350,"servingLabel":"Bowl ~350 ml","featured":false},
  {"id":"ro-rasol","nameEn":"Boiled meat with broth (rasol)","nameRo":"Rasol","aliases":["rasol de pui","rasol porc"],"category":"Traditional","kcal100":165,"p100":18,"c100":0.5,"f100":9.5,"fiber100":0,"servingG":180,"servingLabel":"Meat+veg ~180 g","featured":false},
  {"id":"ro-piftie","nameEn":"Aspic / piftie","nameRo":"Piftie","aliases":["racituri","piftie"],"category":"Traditional","kcal100":125,"p100":14,"c100":2.5,"f100":6.5,"fiber100":0,"servingG":120,"servingLabel":"~120 g","featured":false},
  {"id":"ro-carnaciori-cuptor","nameEn":"Baked small sausages","nameRo":"Cârnăciori la cuptor","aliases":["carnaciori"],"category":"Meat","kcal100":290,"p100":12,"c100":2,"f100":25,"fiber100":0,"servingG":90,"servingLabel":"3 pcs ~90 g","featured":false},
  {"id":"ro-pulpe-pui-pane","nameEn":"Breaded chicken drumsticks","nameRo":"Pulpe de pui pane","aliases":["pui pane"],"category":"Meat","kcal100":235,"p100":16,"c100":12,"f100":14.5,"fiber100":0.6,"servingG":140,"servingLabel":"2 pieces ~140 g","featured":false},
  {"id":"ro-file-pui-pane","nameEn":"Breaded chicken fillet","nameRo":"Piept de pui pane","aliases":["piept pane"],"category":"Meat","kcal100":225,"p100":18,"c100":13,"f100":11,"fiber100":0.5,"servingG":130,"servingLabel":"~130 g","featured":false},
  {"id":"ro-musaca","nameEn":"Moussaka-style bake","nameRo":"Musaca","aliases":["musaca vinete"],"category":"Traditional","kcal100":135,"p100":9.5,"c100":8.5,"f100":7.5,"fiber100":2,"servingG":220,"servingLabel":"Portion ~220 g","featured":false},
  {"id":"ro-dovleac-copt","nameEn":"Baked pumpkin","nameRo":"Dovleac copt","aliases":["dovleac"],"category":"Vegetables","kcal100":38,"p100":1.2,"c100":8.5,"f100":0.2,"fiber100":1.5,"servingG":150,"servingLabel":"~150 g","featured":false},
  {"id":"ro-spanac-sote","nameEn":"Sautéed spinach","nameRo":"Spanac sote","aliases":["spanac"],"category":"Vegetables","kcal100":48,"p100":3.2,"c100":3.5,"f100":2.8,"fiber100":2.2,"servingG":120,"servingLabel":"~120 g","featured":false},
  {"id":"ro-ciuperci-sote","nameEn":"Sautéed mushrooms","nameRo":"Ciuperci sote","aliases":["ciuperci"],"category":"Vegetables","kcal100":52,"p100":2.8,"c100":4.2,"f100":3.2,"fiber100":1.8,"servingG":130,"servingLabel":"~130 g","featured":false},
  {"id":"ro-vinete-scrob","nameEn":"Eggplant salad (salată de vinete)","nameRo":"Salată de vinete","aliases":["salata de vinete","zacusca light"],"category":"Salads","kcal100":88,"p100":1.5,"c100":6.5,"f100":6.5,"fiber100":2.5,"servingG":100,"servingLabel":"~100 g","featured":false},
  {"id":"ro-cuscus","nameEn":"Couscous cooked","nameRo":"Cuscus fiert","aliases":["couscous"],"category":"Staples","kcal100":112,"p100":3.8,"c100":23,"f100":0.2,"fiber100":1.4,"servingG":160,"servingLabel":"~160 g cooked","featured":false},
  {"id":"ro-bulz","nameEn":"Bulz (baked polenta with cheese)","nameRo":"Bulz","aliases":["bulz","mamaliga cu branza la cuptor"],"category":"Traditional","kcal100":195,"p100":9.5,"c100":18,"f100":9.5,"fiber100":1.4,"servingG":180,"servingLabel":"~180 g","featured":true},
  {"id":"ro-salata-icre","nameEn":"Fish roe salad (salată de icre)","nameRo":"Salată de icre","aliases":["salata de icre","tarama"],"category":"Traditional","kcal100":185,"p100":6.5,"c100":4.5,"f100":15.5,"fiber100":0.2,"servingG":45,"servingLabel":"2 tbsp ~45 g","featured":false},
  {"id":"ro-frigarui","nameEn":"Shish kebab / frigărui","nameRo":"Frigărui","aliases":["frigarui","skewers"],"category":"Meat","kcal100":175,"p100":20,"c100":2.5,"f100":9.5,"fiber100":0.5,"servingG":160,"servingLabel":"2 skewers ~160 g","featured":false},
  {"id":"ro-tocana-porc","nameEn":"Pork stew","nameRo":"Tocăniţă de porc","aliases":["tocana porc","tocanita porc"],"category":"Traditional","kcal100":185,"p100":13,"c100":4.2,"f100":12.5,"fiber100":0.8,"servingG":200,"servingLabel":"~200 g","featured":false},
  {"id":"ro-crema-branza","nameEn":"Cream cheese spread","nameRo":"Cremă de brânză","aliases":["crema de branza","philadelphia style"],"category":"Dairy","kcal100":295,"p100":7.5,"c100":4.2,"f100":28,"fiber100":0,"servingG":30,"servingLabel":"2 tbsp ~30 g","featured":false},
  {"id":"ro-napolitane","nameEn":"Wafer biscuits (napolitane)","nameRo":"Napolitane","aliases":["napolitane","wafers"],"category":"Sweets","kcal100":520,"p100":5.5,"c100":62,"f100":27,"fiber100":1.8,"servingG":28,"servingLabel":"2 wafers ~28 g","featured":false},
  {"id":"ro-fructe-uscate","nameEn":"Dried fruit mix","nameRo":"Fructe uscate","aliases":["stafide","merisoare uscate","dried fruit"],"category":"Snacks","kcal100":290,"p100":3.2,"c100":68,"f100":1.5,"fiber100":6.5,"sugar100":55,"servingG":40,"servingLabel":"Small handful ~40 g","featured":false},
  {"id":"ro-branza-dulce","nameEn":"Sweet cow cheese (brânză dulce)","nameRo":"Brânză dulce de vaci","aliases":["branza dulce","sweet cheese"],"category":"Dairy","kcal100":98,"p100":11,"c100":4.5,"f100":4.2,"fiber100":0,"servingG":100,"servingLabel":"~100 g","featured":false},
  {"id":"ro-lapte-cocos","nameEn":"Coconut milk (cooking)","nameRo":"Lapte de cocos","aliases":["lapte cocos","coconut milk can"],"category":"Ingredients","kcal100":190,"p100":2,"c100":3,"f100":20,"fiber100":0,"servingG":60,"servingLabel":"~60 ml cream layer","featured":false},
  {"id":"ro-ulei-masline","nameEn":"Olive oil","nameRo":"Ulei de măsline","aliases":["ulei masline","olive oil"],"category":"Ingredients","kcal100":884,"p100":0,"c100":0,"f100":100,"fiber100":0,"servingG":10,"servingLabel":"1 tsp ~10 g","featured":false},
  {"id":"ro-unt","nameEn":"Butter","nameRo":"Unt","aliases":["butter"],"category":"Dairy","kcal100":717,"p100":0.9,"c100":0.1,"f100":81,"fiber100":0,"servingG":10,"servingLabel":"1 tbsp ~10 g","featured":false},
  {"id":"ro-margarina","nameEn":"Margarine","nameRo":"Margarină","aliases":["margarina"],"category":"Dairy","kcal100":720,"p100":0.5,"c100":0.5,"f100":80,"fiber100":0,"servingG":10,"servingLabel":"~10 g","featured":false},
  {"id":"ro-sunca-prajita","nameEn":"Pan-fried ham slice","nameRo":"Şuncă prăjită","aliases":["sunca prajita","ham fried"],"category":"Meat","kcal100":215,"p100":18,"c100":1.5,"f100":15,"fiber100":0,"servingG":40,"servingLabel":"2 slices ~40 g","featured":false},
  {"id":"ro-caltabos","nameEn":"Liver sausage (estimate)","nameRo":"Caltaboş / lebăr","aliases":["caltabos","lebar"],"category":"Meat","kcal100":315,"p100":14,"c100":3,"f100":27,"fiber100":0,"servingG":50,"servingLabel":"~50 g","featured":false},
  {"id":"ro-jumari","nameEn":"Cracklings (jumări)","nameRo":"Jumări","aliases":["jumari"],"category":"Meat","kcal100":580,"p100":18,"c100":0,"f100":58,"fiber100":0,"servingG":25,"servingLabel":"~25 g","featured":false},
  {"id":"ro-patiserie-savarina","nameEn":"Savarina pastry","nameRo":"Savarina","aliases":["savarina"],"category":"Sweets","kcal100":285,"p100":4.5,"c100":38,"f100":12.5,"fiber100":0.8,"servingG":95,"servingLabel":"1 piece ~95 g","featured":false},
  {"id":"ro-amandina","nameEn":"Amandina cake slice","nameRo":"Amandină","aliases":["amandina"],"category":"Sweets","kcal100":385,"p100":5.5,"c100":42,"f100":21,"fiber100":1.2,"servingG":85,"servingLabel":"Slice ~85 g","featured":false},
  {"id":"ro-fasole-verde","nameEn":"Green beans boiled","nameRo":"Fasole verde fiartă","aliases":["fasole verde","green beans"],"category":"Vegetables","kcal100":35,"p100":1.8,"c100":7.9,"f100":0.3,"fiber100":2.7,"servingG":150,"servingLabel":"~150 g","featured":false},
  {"id":"ro-broccoli-fiert","nameEn":"Boiled broccoli","nameRo":"Broccoli fiert","aliases":["broccoli"],"category":"Vegetables","kcal100":35,"p100":2.4,"c100":7.2,"f100":0.4,"fiber100":2.6,"servingG":150,"servingLabel":"~150 g","featured":false},
  {"id":"ro-conopida-fiarta","nameEn":"Boiled cauliflower","nameRo":"Conopidă fiartă","aliases":["conopida"],"category":"Vegetables","kcal100":32,"p100":2,"c100":5.3,"f100":0.5,"fiber100":2.5,"servingG":150,"servingLabel":"~150 g","featured":false},
  {"id":"ro-morcovi-fierti","nameEn":"Boiled carrots","nameRo":"Morcovi fierţi","aliases":["morcovi"],"category":"Vegetables","kcal100":36,"p100":0.8,"c100":8.2,"f100":0.2,"fiber100":2.5,"servingG":120,"servingLabel":"~120 g","featured":false},
  {"id":"ro-sfecla-salata","nameEn":"Beetroot salad","nameRo":"Salată de sfeclă","aliases":["salata de sfecla","beet salad"],"category":"Salads","kcal100":72,"p100":1.8,"c100":12,"f100":2.2,"fiber100":2.2,"servingG":120,"servingLabel":"~120 g","featured":false},
  {"id":"ro-hrean","nameEn":"Horseradish (grated)","nameRo":"Hrean","aliases":["hrean"],"category":"Condiments","kcal100":65,"p100":2.5,"c100":12,"f100":0.7,"fiber100":3.3,"servingG":15,"servingLabel":"1 tsp ~15 g","featured":false},
  {"id":"ro-mustar","nameEn":"Mustard","nameRo":"Muştar","aliases":["mustar"],"category":"Condiments","kcal100":95,"p100":5,"c100":8.5,"f100":4.5,"fiber100":3.5,"servingG":15,"servingLabel":"1 tbsp ~15 g","featured":false},
  {"id":"ro-mujdei","nameEn":"Mujdei (garlic sauce)","nameRo":"Mujdei de usturoi","aliases":["mujdei","usturoi zdrobit"],"category":"Condiments","kcal100":185,"p100":1.2,"c100":3.5,"f100":18.5,"fiber100":0.3,"servingG":25,"servingLabel":"~25 g","featured":false}
]
